{"inkVersion":21,"root":[[{"->":"UXReview"},["done",{"#f":5,"#n":"g-0"}],null],"done",{"UXReview":[{"->":".^.FocusCheck"},{"FocusCheck":["^Prioritizing core gameplay UX. Any issues observed? ","#","^C:Dog:0","/#","\n",{"->":".^.^.VisualUpdates"},{"#f":1}],"VisualUpdates":["^UI animations require 3 more days for proper implementation. The current timeline is unrealistic. ","#","^C:Peacock:0","/#","\n","^We must lock technical specifications today. Further delays will compromise the entire sprint. ","#","^C:Cat:0","/#","\n","^Let's practice active listening. Peacock first: What essential element needs protection? ","#","^C:Dog:0","/#","\n",{"->":".^.^.ActiveListening_Explanation"},{"#f":1}],"ActiveListening_Explanation":["^Active listening means restating concerns to ensure mutual understanding. Three components:","\n","^1. Paraphrasing content","\n","^2. Identifying emotions","\n","^3. Asking clarifying questions","\n","^Now try restating Cat's position, Peacock. ","#","^C:Dog:0","/#","\n",{"->":".^.^.ConflictResolution1"},{"#f":1}],"ConflictResolution1":["^(paraphrasing) You're worried delayed animations will push back QA cycles... ","#","^C:Peacock:0","/#","\n","^Yes, we need 48h for regression testing before launch. ","#","^C:Cat:0","/#","\n",{"->":".^.^.Compromise"},{"#f":1}],"Compromise":["^Proposal: Tiered implementation. Core UI today, secondary animations in v1.1 patch. ","#","^C:Dog:0","/#","\n","^Acceptable if we document deferred assets clearly. ","#","^C:Peacock:0","/#","\n","^Agreed. I'll create the technical debt tracker. ","#","^C:Cat:0","/#","\n",{"->":".^.^.AudioAdjustments"},{"#f":1}],"AudioAdjustments":["^Music adjustments conflict with balance testing priorities. Numerical tuning must take precedence. ","#","^C:Fox:0","/#","\n","^Emotional resonance through audio is equally vital for player retention. ","#","^C:Lark:0","/#","\n",{"->":".^.^.ABC_Explanation"},{"#f":1}],"ABC_Explanation":["^Let's apply Ellis's ABC model:","\n","^A - Activating Event (surface conflict)","\n","^B - Beliefs (underlying assumptions)","\n","^C - Consequences (emotional/behavioral outcomes)","\n","^Fox, identify the 'A' in this situation. ","#","^C:Dog:0","/#","\n",{"->":".^.^.ABC_Application"},{"#f":1}],"ABC_Application":["^A: Audio changes requiring rebalancing. ","#","^C:Fox:0","/#","\n","^Lark's B: \"Emotion drives retention\" vs Fox's B: \"Numbers ensure fairness\" ","#","^C:Dog:0","/#","\n","^Consequence: Mutual frustration. Now seek cognitive restructuring. ","#","^C:Dog:0","/#","\n",{"->":".^.^.Reframe"},{"#f":1}],"Reframe":["^Shared goal: Engagement through balanced emotional/numerical design. ","#","^C:Dog:0","/#","\n","^Solution: Dynamic music scaling with achievement thresholds. ","#","^C:Dog:0","/#","\n",{"->":".^.^.Synergy"},{"#f":1}],"Synergy":["^I can map BPM changes to XP gain rates. Technical feasible? ","#","^C:Lark:0","/#","\n","^Yes, using existing progression APIs. Requires 18h implementation. ","#","^C:Cat:0","/#","\n","^This preserves balance while adding emotional depth. Approved. ","#","^C:Fox:0","/#","\n",{"->":".^.^.TechStability"},{"#f":1}],"TechStability":["^System optimizations completed. Audio-Progress API integration passed stress tests. ","#","^C:Cat:0","/#","\n",{"->":".^.^.BalanceTuning"},{"#f":1}],"BalanceTuning":["^Adjusted values account for new audio dynamics. Testing thresholds updated. ","#","^C:Fox:0","/#","\n",{"->":".^.^.NarrativeIntegration"},{"#f":1}],"NarrativeIntegration":["^Branching paths now reflect both statistical outcomes and emotional tones. ","#","^C:Deer:0","/#","\n",{"->":".^.^.Debugging"},{"#f":1}],"Debugging":["^Latency reduced 60% through coordinated debugging sessions. All systems nominal. ","#","^C:Capybara:0","/#","\n","end",{"#f":1}],"#f":1}],"#f":1}],"listDefs":{}}